Workbook

Sheet Assumptions
A1: USDe / sUSDe Delta-Neutral Model — Assumptions
A2: Input | B2: Value | C2: Notes
A3: As of Date | B3: 2025-09-15 | C3: Model date stamp
A4: Capital (USD) | B4: 10000 | C4: Deployable capital for the strategy
A5: Mint Path | B5: Primary | C5: Primary/Secondary (direct mint vs. market acquisition)
A6: Base Asset | B6: sUSDe | C6: USDe or sUSDe held
A7: sUSDe Boost On/Off | B7: On | C7: Toggle reward-accruing sUSDe (On/Off)
A8: ETH Staking APR (structural) | B8: 0.031 | C8: Long-run ETH staking APR (31 bps = 3.1%)
A9: Funding APY (base case) | B9: 0.1 | C9: Annualized perp funding captured by short hedge (10% default)
A10: Funding APY (bear case) | B10: -0.02 | C10: Annualized funding paid by shorts in bear case (-2%)
A11: Funding APY (bull case) | B11: 0.18 | C11: Annualized funding in bull case (+18%)
A12: Protocol/Custody Fee (annual) | B12: 0.005 | C12: Blended custody/off-exchange/ops fee assumption
A13: Execution/Gas Slippage (bps) | B13: 10 | C13: One-time slippage for mint/redeem (basis points)
A14: Expected Holding Period (days) | B14: 90 | C14: Planned duration before reassessment/exit
A15: Utilization (capital actually deployed) | B15: 0.98 | C15: Allow for operational cash buffer
A16: Reserve/Insurance Buffer (%) | B16: 0.02 | C16: Conservative haircut for tail risks / reserves

Sheet Position & Yield
A1: Position Sizing & Expected Yield
A2: Metric | B2: Value | C2: Notes
A3: Capital (USD) | B3: =Assumptions!B4 -> 10000
A4: Utilization | B4: =Assumptions!B15 -> 0.98
A5: Deployed Capital (USD) | B5: =B3*B4 -> 9800 | C5: Capital actually deployed into USDe/sUSDe
A6: One-time Slippage (bps) | B6: =Assumptions!B13 -> 10
A7: Slippage Cost (USD) | B7: =B5*B6*0.0001 -> 9.8 | C7: One-off execution cost
A8: Protocol/Custody Fee (annual) | B8: =Assumptions!B12 -> 0.005
A9: Holding Period (days) | B9: =Assumptions!B14 -> 90
A10: Holding Period (years) | B10: =B9/365 -> 0.24657534
A11: ETH Staking APR | B11: =Assumptions!B8 -> 0.031 | C11: Structural source
A12: Funding APY (Base) | B12: =Assumptions!B9 -> 0.1 | C12: Market-dependent
A13: sUSDe Boost On? | B13: =Assumptions!B7 -> On | C13: On/Off toggle read (for clarity)
A14: Reserve/Insurance Buffer | B14: =Assumptions!B16 -> 0.02
A16: Gross Yield Components (Annualized)
A17: ETH Staking Yield | B17: =B11 -> 0.031 | C17: If backing includes staked ETH
A18: Funding Yield | B18: =B12 -> 0.1 | C18: Perp funding captured by short hedge
A19: Total Gross Yield (Annualized) | B19: =B17+B18 -> 0.131 | C19: Sum of components
A21: Net Yield (after costs)
A22: Annualized Net Yield | B22: =B19-B8 -> 0.126 | C22: Gross minus annual fees
A23: Holding-Period Net Return | B23: =B22*B10-B7/B3-B14 -> 0.010088493 | C23: Pro-rata yield minus fees, slippage, and reserve buffer

Sheet StressTests
A1: Stress Tests — Funding & Slippage Sensitivity
A2: Funding APY | B2: ETH Staking Yield | C2: Capital (USD) | D2: Annual Fee | E2: Holding (yrs) | F2: Slippage ($) | G2: Reserve Buffer | H2: Holding-Period Net Return
A3: -0.05 | B3: =Assumptions!$B$8 -> 0.031 | C3: ='Position & Yield'!$B$3 -> 10000 | D3: =Assumptions!$B$12 -> 0.005 | E3: ='Position & Yield'!$B$10 -> 0.24657534 | F3: ='Position & Yield'!$B$7 -> 9.8 | G3: =Assumptions!$B$16 -> 0.02 | H3: =(B3+A3-D3)*E3-F3/C3-G3 -> -0.026897808
A4: -0.02 | B4: =Assumptions!$B$8 -> 0.031 | C4: ='Position & Yield'!$B$3 -> 10000 | D4: =Assumptions!$B$12 -> 0.005 | E4: ='Position & Yield'!$B$10 -> 0.24657534 | F4: ='Position & Yield'!$B$7 -> 9.8 | G4: =Assumptions!$B$16 -> 0.02 | H4: =(B4+A4-D4)*E4-F4/C4-G4 -> -0.019500548
A5: 0 | B5: =Assumptions!$B$8 -> 0.031 | C5: ='Position & Yield'!$B$3 -> 10000 | D5: =Assumptions!$B$12 -> 0.005 | E5: ='Position & Yield'!$B$10 -> 0.24657534 | F5: ='Position & Yield'!$B$7 -> 9.8 | G5: =Assumptions!$B$16 -> 0.02 | H5: =(B5+A5-D5)*E5-F5/C5-G5 -> -0.014569041
A6: 0.05 | B6: =Assumptions!$B$8 -> 0.031 | C6: ='Position & Yield'!$B$3 -> 10000 | D6: =Assumptions!$B$12 -> 0.005 | E6: ='Position & Yield'!$B$10 -> 0.24657534 | F6: ='Position & Yield'!$B$7 -> 9.8 | G6: =Assumptions!$B$16 -> 0.02 | H6: =(B6+A6-D6)*E6-F6/C6-G6 -> -0.002240274
A7: 0.1 | B7: =Assumptions!$B$8 -> 0.031 | C7: ='Position & Yield'!$B$3 -> 10000 | D7: =Assumptions!$B$12 -> 0.005 | E7: ='Position & Yield'!$B$10 -> 0.24657534 | F7: ='Position & Yield'!$B$7 -> 9.8 | G7: =Assumptions!$B$16 -> 0.02 | H7: =(B7+A7-D7)*E7-F7/C7-G7 -> 0.010088493
A8: 0.15 | B8: =Assumptions!$B$8 -> 0.031 | C8: ='Position & Yield'!$B$3 -> 10000 | D8: =Assumptions!$B$12 -> 0.005 | E8: ='Position & Yield'!$B$10 -> 0.24657534 | F8: ='Position & Yield'!$B$7 -> 9.8 | G8: =Assumptions!$B$16 -> 0.02 | H8: =(B8+A8-D8)*E8-F8/C8-G8 -> 0.02241726
A9: 0.2 | B9: =Assumptions!$B$8 -> 0.031 | C9: ='Position & Yield'!$B$3 -> 10000 | D9: =Assumptions!$B$12 -> 0.005 | E9: ='Position & Yield'!$B$10 -> 0.24657534 | F9: ='Position & Yield'!$B$7 -> 9.8 | G9: =Assumptions!$B$16 -> 0.02 | H9: =(B9+A9-D9)*E9-F9/C9-G9 -> 0.034746027

Sheet RiskDashboard
A1: Risk Dashboard — Qualitative Scoring (1=Low, 5=High)
A2: Risk Category | B2: Score (1-5) | C2: Notes / Mitigants
A3: Funding Rate Volatility | B3: 3 | C3: Monitor 7DMA funding; reduce exposure when negative
A4: Counterparty/CEX Risk | B4: 4 | C4: Prefer off-exchange custody; diversify venues
A5: Smart Contract Risk | B5: 3 | C5: Audit review; bug bounties; insurance where possible
A6: Liquidity/Redemption Risk | B6: 3 | C6: Track USDe secondary liquidity + mint queues
A7: Oracle/Operational Risk | B7: 3 | C7: Alerting; runbooks; perform dry-run migrations
A8: Regulatory/Compliance | B8: 4 | C8: Sanctions/KYC policies; jurisdictional fit; tax
A9: Market Gap Risk (Hedge Slippage) | B9: 3 | C9: Use conservative sizing; crisis playbook

Sheet Notes
B2: Notes, Glossary & Caveats
B3: • This model approximates the economics of a delta-neutral USDe/sUSDe strategy (Ethena).
B4: • Yield sources: ETH staking APR (structural) + perpetual funding (market-dependent).
B5: • Perpetual funding varies; past positivity does not guarantee future results.
B6: • Costs include custody/ops fees, slippage, and a reserve haircut for tail risk.
B7: • StressTests tab lets you explore negative funding scenarios and fee spikes.
B8: • Always verify live yields, mint/redeem fees, and venue-specific terms before deployment.
